LICENSE
README.md
setup.py
chromatic/__init__.py
chromatic/imports.py
chromatic/version.py
chromatic/archives/__init__.py
chromatic/archives/mast.py
chromatic/rainbows/__init__.py
chromatic/rainbows/multi.py
chromatic/rainbows/rainbow.py
chromatic/rainbows/simulated.py
chromatic/rainbows/withmodel.py
chromatic/rainbows/actions/__init__.py
chromatic/rainbows/actions/align_wavelengths.py
chromatic/rainbows/actions/attach_model.py
chromatic/rainbows/actions/binning.py
chromatic/rainbows/actions/compare.py
chromatic/rainbows/actions/concatenate.py
chromatic/rainbows/actions/flag_outliers.py
chromatic/rainbows/actions/fold.py
chromatic/rainbows/actions/inflate_uncertainty.py
chromatic/rainbows/actions/inject_noise.py
chromatic/rainbows/actions/inject_outliers.py
chromatic/rainbows/actions/inject_spectrum.py
chromatic/rainbows/actions/inject_systematics.py
chromatic/rainbows/actions/inject_transit.py
chromatic/rainbows/actions/normalization.py
chromatic/rainbows/actions/operations.py
chromatic/rainbows/actions/remove_trends.py
chromatic/rainbows/actions/shift.py
chromatic/rainbows/actions/trim.py
chromatic/rainbows/converters/__init__.py
chromatic/rainbows/converters/for_altair.py
chromatic/rainbows/get/__init__.py
chromatic/rainbows/get/fluxlike/__init__.py
chromatic/rainbows/get/fluxlike/subset.py
chromatic/rainbows/get/timelike/__init__.py
chromatic/rainbows/get/timelike/average_lightcurve.py
chromatic/rainbows/get/timelike/median_lightcurve.py
chromatic/rainbows/get/timelike/subset.py
chromatic/rainbows/get/timelike/time.py
chromatic/rainbows/get/wavelike/__init__.py
chromatic/rainbows/get/wavelike/average_spectrum.py
chromatic/rainbows/get/wavelike/expected_uncertainty.py
chromatic/rainbows/get/wavelike/measured_scatter.py
chromatic/rainbows/get/wavelike/measured_scatter_in_bins.py
chromatic/rainbows/get/wavelike/median_spectrum.py
chromatic/rainbows/get/wavelike/spectral_resolution.py
chromatic/rainbows/get/wavelike/subset.py
chromatic/rainbows/helpers/__init__.py
chromatic_lightcurves.egg-info/PKG-INFO
chromatic_lightcurves.egg-info/SOURCES.txt
chromatic_lightcurves.egg-info/dependency_links.txt
chromatic_lightcurves.egg-info/not-zip-safe
chromatic_lightcurves.egg-info/requires.txt
chromatic_lightcurves.egg-info/top_level.txt